setup.cfg
setup.py
python_spoj.egg-info/PKG-INFO
python_spoj.egg-info/SOURCES.txt
python_spoj.egg-info/dependency_links.txt
python_spoj.egg-info/entry_points.txt
python_spoj.egg-info/not-zip-safe
python_spoj.egg-info/requires.txt
python_spoj.egg-info/top_level.txt
spoj/__init__.py
spoj/cSpinner.py
spoj/cli.py
spoj/config.py
spoj/lang.py
spoj/spoj.py
spoj/urls.py
spoj/utils.py