Metadata-Version: 1.1
Name: python-spoj
Version: 0.5.3
Summary: A command line tool for spoj
Home-page: https://github.com/DheerendraRathor/python-spoj
Author: Dheerendra Rathor
Author-email: dheeru.rathor14@gmail.com
License: BSD
Platform: any
Classifier: Development Status :: 4 - Beta
Classifier: Environment :: Console
Classifier: Intended Audience :: Developers
Classifier: License :: OSI Approved :: BSD License
Classifier: Operating System :: POSIX
Classifier: Operating System :: MacOS
Classifier: Operating System :: Unix
Classifier: Operating System :: Microsoft :: Windows
Classifier: Programming Language :: Python
Classifier: Programming Language :: Python :: 2
Classifier: Topic :: Software Development :: Libraries :: Python Modules
